awscdk_81_patch/__init__.py
awscdk_81_patch/py.typed
awscdk_81_patch/_jsii/__init__.py
awscdk_81_patch/_jsii/awscdk-81-patch@1.1.1.jsii.tgz
awscdk_81_patch-1.1.1.dist-info/METADATA
awscdk_81_patch-1.1.1.dist-info/WHEEL
awscdk_81_patch-1.1.1.dist-info/top_level.txt
awscdk_81_patch-1.1.1.dist-info/RECORD
