Metadata-Version: 2.1
Name: awscdk-81-patch
Version: 1.1.1
Summary: awscdk-81-patch
Home-page: https://github.com/eladb/awscdk-81-patch.git
Author: Elad Ben-Israel<benisrae@amazon.com>
License: Apache-2.0
Project-URL: Source, https://github.com/eladb/awscdk-81-patch.git
Platform: UNKNOWN
Classifier: Intended Audience :: Developers
Classifier: Operating System :: OS Independent
Classifier: Programming Language :: JavaScript
Classifier: Programming Language :: Python :: 3 :: Only
Classifier: Programming Language :: Python :: 3.6
Classifier: Programming Language :: Python :: 3.7
Classifier: Programming Language :: Python :: 3.8
Classifier: Programming Language :: Python :: 3.9
Classifier: Typing :: Typed
Classifier: Development Status :: 5 - Production/Stable
Classifier: License :: OSI Approved
Requires-Python: >=3.6
Requires-Dist: aws-cdk.lambda-layer-awscli (==1.81.0)
Requires-Dist: aws-cdk.lambda-layer-kubectl (==1.81.0)
Requires-Dist: jsii (<2.0.0,>=1.16.0)
Requires-Dist: publication (>=0.0.3)
